diffit/VERSION
diffit/__init__.py
diffit/__main__.py
diffit/py.typed
diffit/datastore/__init__.py
diffit/datastore/spark.py
diffit/reporter/__init__.py
diffit/reporter/rangefilter.py
diffit/schema/__init__.py
diffit/schema/dummy.py
diffit/utils/__init__.py
diffit-0.1.5.dist-info/LICENSE.md
diffit-0.1.5.dist-info/METADATA
diffit-0.1.5.dist-info/WHEEL
diffit-0.1.5.dist-info/entry_points.txt
diffit-0.1.5.dist-info/top_level.txt
diffit-0.1.5.dist-info/RECORD
