Metadata-Version: 2.1
Name: diffit
Version: 0.1.5
Summary: Diff-it: Spark Dataframe Differ
Home-page: https://github.com/loum/diffit
Author: Lou Markovski
Author-email: lou.markovski@gmail.com
License: MIT
Classifier: Development Status :: 5 - Production/Stable
Classifier: Environment :: Console
Classifier: Environment :: MacOS X
Classifier: Intended Audience :: Developers
Classifier: Topic :: Software Development :: Build Tools
Classifier: License :: OSI Approved :: MIT License
Classifier: Natural Language :: English
Classifier: Operating System :: POSIX :: Linux
Classifier: Operating System :: MacOS :: MacOS X
Classifier: Programming Language :: Python :: 3
Requires-Python: >=3
License-File: LICENSE.md
Requires-Dist: filester
Requires-Dist: logga
Requires-Dist: typer[all]
Provides-Extra: dev
Requires-Dist: pyspark ==3.* ; extra == 'dev'
Requires-Dist: pytest ; extra == 'dev'
Requires-Dist: pytest-cov ; extra == 'dev'
Requires-Dist: pytest-sugar ; extra == 'dev'
